Workbook
Name Slicer_Region1: #N/A
Name Slicer_Category2: #N/A
Name Slicer_Year: #N/A

Sheet Excel_Sales_Dataset
A1: Order_ID | B1: Order_Date | C1: Region | D1: State | E1: Category | F1: Sub_Category | G1: Customer_Type | H1: Sales | I1: Quantity | J1: Discount | K1: Profit
A2: 100001 | B2: 44927 | C2: East | D2: Maharashtra | E2: Electronics | F2: Storage | G2: Corporate | H2: 25914.11 | I2: 4 | J2: 0.3 | K2: -2591.41
A3: 100002 | B3: 44927.042 | C3: West | D3: Maharashtra | E3: Furniture | F3: Phones | G3: Corporate | H3: 26787.84 | I3: 6 | J3: 0.25 | K3: -1339.39
A4: 100003 | B4: 44927.083 | C4: North | D4: Tamil Nadu | E4: Office Supplies | F4: Laptops | G4: Retail | H4: 29815.11 | I4: 1 | J4: 0.07 | K4: 3875.96
A5: 100004 | B5: 44927.125 | C5: East | D5: West Bengal | E5: Electronics | F5: Storage | G5: Small Business | H5: 41265.2 | I5: 9 | J5: 0.27 | K5: -2888.56
A6: 100005 | B6: 44927.167 | C6: East | D6: West Bengal | E6: Furniture | F6: Storage | G6: Corporate | H6: 15297.26 | I6: 4 | J6: 0.18 | K6: 305.95
A7: 100006 | B7: 44927.208 | C7: West | D7: Tamil Nadu | E7: Electronics | F7: Phones | G7: Small Business | H7: 13179.99 | I7: 5 | J7: 0 | K7: 2636
A8: 100007 | B8: 44927.25 | C8: North | D8: Delhi | E8: Electronics | F8: Phones | G8: Corporate | H8: 39892.54 | I8: 8 | J8: 0.1 | K8: 3989.25
A9: 100008 | B9: 44927.292 | C9: North | D9: Maharashtra | E9: Furniture | F9: Binders | G9: Retail | H9: 36076.57 | I9: 6 | J9: 0.01 | K9: 6854.55
A10: 100009 | B10: 44927.333 | C10: East | D10: Maharashtra | E10: Office Supplies | F10: Phones | G10: Retail | H10: 11667.94 | I10: 3 | J10: 0.03 | K10: 1983.55
A11: 100010 | B11: 44927.375 | C11: South | D11: Tamil Nadu | E11: Furniture | F11: Storage | G11: Corporate | H11: 541.4 | I11: 8 | J11: 0.05 | K11: 81.21
A12: 100011 | B12: 44927.417 | C12: East | D12: Tamil Nadu | E12: Furniture | F12: Chairs | G12: Corporate | H12: 33463.85 | I12: 6 | J12: 0.15 | K12: 1673.19
A13: 100012 | B13: 44927.458 | C13: East | D13: Delhi | E13: Furniture | F13: Phones | G13: Corporate | H13: 8280.31 | I13: 2 | J13: 0.11 | K13: 745.23
... A12001: 112000 | B12001: 45426.958 | C12001: East | D12001: Gujarat | E12001: Electronics | F12001: Phones | G12001: Corporate | H12001: 14875.46 | I12001: 4 | J12001: 0.1 | K12001: 1487.55

Sheet operational
A1: Order_ID | B1: Order_Date | C1: Region | D1: State | E1: Category | F1: Sub_Category | G1: Customer_Type | H1: Sales | I1: Quantity | J1: Discount | K1: Profit | L1: Month | M1: Year | N1: profit (%)
A2: 100001 | B2: 44927 | C2: East | D2: Maharashtra | E2: Electronics | F2: Storage | G2: Corporate | H2: 25914.11 | I2: 4 | J2: 0.3 | K2: -2591.41 | L2: =TEXT(B2,"mmm") -> Jan | M2: =YEAR(B2) -> 2023 | N2: =(K2/H2) -> -0.099999961
A3: 100002 | B3: 44927.042 | C3: West | D3: Maharashtra | E3: Furniture | F3: Phones | G3: Corporate | H3: 26787.84 | I3: 6 | J3: 0.25 | K3: -1339.39 | L3: =TEXT(B3,"mmm") -> Jan | M3: =YEAR(B3) -> 2023 | N3: =(K3/H3) -> -0.049999925
A4: 100003 | B4: 44927.083 | C4: North | D4: Tamil Nadu | E4: Office Supplies | F4: Laptops | G4: Retail | H4: 29815.11 | I4: 1 | J4: 0.07 | K4: 3875.96 | L4: =TEXT(B4,"mmm") -> Jan | M4: =YEAR(B4) -> 2023 | N4: =(K4/H4) -> 0.12999986
A5: 100004 | B5: 44927.125 | C5: East | D5: West Bengal | E5: Electronics | F5: Storage | G5: Small Business | H5: 41265.2 | I5: 9 | J5: 0.27 | K5: -2888.56 | L5: =TEXT(B5,"mmm") -> Jan | M5: =YEAR(B5) -> 2023 | N5: =(K5/H5) -> -0.069999903
A6: 100005 | B6: 44927.167 | C6: East | D6: West Bengal | E6: Furniture | F6: Storage | G6: Corporate | H6: 15297.26 | I6: 4 | J6: 0.18 | K6: 305.95 | L6: =TEXT(B6,"mmm") -> Jan | M6: =YEAR(B6) -> 2023 | N6: =(K6/H6) -> 0.020000314
A7: 100006 | B7: 44927.208 | C7: West | D7: Tamil Nadu | E7: Electronics | F7: Phones | G7: Small Business | H7: 13179.99 | I7: 5 | J7: 0 | K7: 2636 | L7: =TEXT(B7,"mmm") -> Jan | M7: =YEAR(B7) -> 2023 | N7: =(K7/H7) -> 0.20000015
A8: 100007 | B8: 44927.25 | C8: North | D8: Delhi | E8: Electronics | F8: Phones | G8: Corporate | H8: 39892.54 | I8: 8 | J8: 0.1 | K8: 3989.25 | L8: =TEXT(B8,"mmm") -> Jan | M8: =YEAR(B8) -> 2023 | N8: =(K8/H8) -> 0.0999999
A9: 100008 | B9: 44927.292 | C9: North | D9: Maharashtra | E9: Furniture | F9: Binders | G9: Retail | H9: 36076.57 | I9: 6 | J9: 0.01 | K9: 6854.55 | L9: =TEXT(B9,"mmm") -> Jan | M9: =YEAR(B9) -> 2023 | N9: =(K9/H9) -> 0.19000005
A10: 100009 | B10: 44927.333 | C10: East | D10: Maharashtra | E10: Office Supplies | F10: Phones | G10: Retail | H10: 11667.94 | I10: 3 | J10: 0.03 | K10: 1983.55 | L10: =TEXT(B10,"mmm") -> Jan | M10: =YEAR(B10) -> 2023 | N10: =(K10/H10) -> 0.17000002
A11: 100010 | B11: 44927.375 | C11: South | D11: Tamil Nadu | E11: Furniture | F11: Storage | G11: Corporate | H11: 541.4 | I11: 8 | J11: 0.05 | K11: 81.21 | L11: =TEXT(B11,"mmm") -> Jan | M11: =YEAR(B11) -> 2023 | N11: =(K11/H11) -> 0.15
A12: 100011 | B12: 44927.417 | C12: East | D12: Tamil Nadu | E12: Furniture | F12: Chairs | G12: Corporate | H12: 33463.85 | I12: 6 | J12: 0.15 | K12: 1673.19 | L12: =TEXT(B12,"mmm") -> Jan | M12: =YEAR(B12) -> 2023 | N12: =(K12/H12) -> 0.049999925
A13: 100012 | B13: 44927.458 | C13: East | D13: Delhi | E13: Furniture | F13: Phones | G13: Corporate | H13: 8280.31 | I13: 2 | J13: 0.11 | K13: 745.23 | L13: =TEXT(B13,"mmm") -> Jan | M13: =YEAR(B13) -> 2023 | N13: =(K13/H13) -> 0.090000254
... A12001: 112000 | B12001: 45426.958 | C12001: East | D12001: Gujarat | E12001: Electronics | F12001: Phones | G12001: Corporate | H12001: 14875.46 | I12001: 4 | J12001: 0.1 | K12001: 1487.55 | L12001: =TEXT(B12001,"mmm") -> May | M12001: =YEAR(B12001) -> 2024 | N12001: =(K12001/H12001) -> 0.10000027

Sheet KPI_Cal
A1: KPIs | B1: Values
A2: Total Sales | B2: =Pivots!E21 -> 3.0458673e+08
A3: Total Profit | B3: =Pivots!F21 -> 15168236
A4: Total Orders | B4: =Pivots!G21 -> 12000
A5: Average Order Value | B5: =B2/B4 -> 25382.228
A6: Profit Margin % | B6: =B3/B2 -> 0.0497994

Sheet Dashboard
A1: Sales Performance Dashboard (Jan 2023 – May 2024)
B2: =KPI_Cal!B2 -> 3.0458673e+08 | G2: =KPI_Cal!B3 -> 15168236 | L2: =KPI_Cal!B6 -> 0.0497994
B4: Total Sales | G4: Total Profit | L4: Profit Margin %
D5: =KPI_Cal!B4 -> 12000 | I5: =KPI_Cal!B5 -> 25382.228
D7: Total Orders | I7: Average Order Value

Sheet Pivots
A3: Region | B3: Total Sales | F3: Category | G3: Total Profit
A4: North | B4: 77622610 | F4: Electronics | G4: 5048109.2
A5: East | B5: 76895407 | F5: Furniture | G5: 4986725.9
A6: West | B6: 75213049 | F6: Office Supplies | G6: 5133401.2
A7: South | B7: 74855667
A8: Grand Total | B8: 3.0458673e+08
A10: Product | B10: Total Sales | C10: Total Profit | F10: Customer_Type | G10: total Sales | I10: Year | J10: Month | K10: Sales amount
A11: Binders | B11: 52916620 | C11: 2658889 | F11: Corporate | G11: 1.0532024e+08 | I11: 2023 | K11: 2.225102e+08
A12: Storage | B12: 51148063 | C12: 2529150.1 | F12: Retail | G12: 99479383 | J12: Jan | K12: 18769938
A13: Chairs | B13: 50884779 | C13: 2615827.6 | F13: Small Business | G13: 99787113 | J13: Feb | K13: 17033516
A14: Tables | B14: 50428780 | C14: 2559611.5 | J14: Mar | K14: 18809574
A15: Laptops | B15: 50116502 | C15: 2455908.3 | J15: Apr | K15: 18254059
A16: Phones | B16: 49091988 | C16: 2348849.8 | J16: May | K16: 19078935
A17: Grand Total | B17: 3.0458673e+08 | C17: 15168236 | J17: Jun | K17: 18393135
J18: Jul | K18: 19255331
J19: Aug | K19: 19022738
E20: Total Sales | F20: Total Profit | G20: Total Orders | J20: Sep | K20: 18142957
E21: 3.0458673e+08 | F21: 15168236 | G21: 12000 | J21: Oct | K21: 18970326
J22: Nov | K22: 18248267
J23: Dec | K23: 18531424
I24: 2024 | K24: 82076534
J25: Jan | K25: 18899983
J26: Feb | K26: 18058995
J27: Mar | K27: 18556651
J28: Apr | K28: 18162671
J29: May | K29: 8398234.3
I30: Grand Total | K30: 3.0458673e+08
